fionn/__init__.py
fionn/__init__.pyi
fionn/ext.pyi
fionn/fionn.abi3.so
fionn/py.typed
fionn-0.1.0.dist-info/METADATA
fionn-0.1.0.dist-info/WHEEL
fionn-0.1.0.dist-info/RECORD
