Metadata-Version: 2.4
Name: fionn
Version: 0.1.0
Classifier: Development Status :: 4 - Beta
Classifier: Intended Audience :: Developers
Classifier: License :: OSI Approved :: MIT License
Classifier: License :: OSI Approved :: Apache Software License
Classifier: Operating System :: OS Independent
Classifier: Programming Language :: Python :: 3
Classifier: Programming Language :: Python :: 3.9
Classifier: Programming Language :: Python :: 3.10
Classifier: Programming Language :: Python :: 3.11
Classifier: Programming Language :: Python :: 3.12
Classifier: Programming Language :: Python :: 3.13
Classifier: Programming Language :: Python :: Implementation :: CPython
Classifier: Programming Language :: Rust
Classifier: Topic :: Software Development :: Libraries :: Python Modules
Classifier: Topic :: Text Processing :: General
Classifier: Typing :: Typed
Requires-Dist: fionn[numpy,dev] ; extra == 'all'
Requires-Dist: pytest>=8.0 ; extra == 'dev'
Requires-Dist: pytest-benchmark>=4.0 ; extra == 'dev'
Requires-Dist: hypothesis>=6.100 ; extra == 'dev'
Requires-Dist: orjson>=3.10 ; extra == 'dev'
Requires-Dist: mypy>=1.10 ; extra == 'dev'
Requires-Dist: ruff>=0.6 ; extra == 'dev'
Requires-Dist: numpy>=1.20 ; extra == 'numpy'
Provides-Extra: all
Provides-Extra: dev
Provides-Extra: numpy
Summary: Fast JSON library with SIMD acceleration - drop-in orjson replacement + extended features
Keywords: json,simd,orjson,jsonl,isonl,crdt,gron,diff
Author-email: Darach Ennis <darach@gmail.com>
License: MIT OR Apache-2.0
Requires-Python: >=3.9
Project-URL: Documentation, https://github.com/darach/fionn#readme
Project-URL: Homepage, https://github.com/darach/fionn
Project-URL: Issues, https://github.com/darach/fionn/issues
Project-URL: Repository, https://github.com/darach/fionn
